neurosift/TemporaryDirectory.py
neurosift/__init__.py
neurosift/cli.py
neurosift/codecs/MP4AVCCodec.py
neurosift/codecs/__init__.py
neurosift/local-file-access-js/README.md
neurosift/local-file-access-js/package.json
neurosift/local-file-access-js/src/index.js
neurosift-0.2.15.dist-info/METADATA
neurosift-0.2.15.dist-info/WHEEL
neurosift-0.2.15.dist-info/entry_points.txt
neurosift-0.2.15.dist-info/top_level.txt
neurosift-0.2.15.dist-info/RECORD
